{"data":{"apiPageJson":{"pid":"MenuItem","parentPid":"typedef","title":"Typedef","items":[{"pid":"MenuItem","type":"overview","override":false,"deprecated":false,"name":"MenuItem","types":{"prefix":"","names":["object"],"isOptional":false},"description":"","codeInfo":{"filename":"contextmenu.js","lineNum":23,"linkUrl":"https://github.com/nhnent/tui.context-menu/blob/v2.1.3/src/js/contextmenu.js"},"sees":[""],"todos":[""],"augments":[""],"params":[{"name":"title","description":"title of menu item","defaultVal":null,"types":{"prefix":"","names":["string"],"isOptional":false},"properties":null},{"name":"command","description":"string for alternative of using title to command","defaultVal":null,"types":{"prefix":"","names":["string"],"isOptional":true},"properties":null},{"name":"separator","description":"set true then this menu will use<br> separator","defaultVal":null,"types":{"prefix":"","names":["boolean"],"isOptional":true},"properties":null},{"name":"menu","description":"you can define submenu recursivly","defaultVal":null,"types":{"prefix":"","names":["Array"],"isOptional":true},"properties":null},{"name":"","description":"","defaultVal":"","types":{"prefix":"","names":[""],"isOptional":false},"properties":[{"name":"","description":"","defaultVal":"","types":{"prefix":"","names":[""],"isOptional":false},"properties":[{"name":"","description":"","defaultVal":"","types":{"prefix":"","names":[""],"isOptional":false},"properties":[{"name":"","description":"","defaultVal":"","types":{"prefix":"","names":[""],"isOptional":false}}]}]}]}],"examples":[{"description":"","code":""}],"returns":[{"types":{"prefix":"","names":[""],"isOptional":false},"description":""}]}]}},"pageContext":{"id":"MenuItem","filename":""}}